{"events":[{"id":"57baaa91-5e8f-4eb2-81ba-9af7e30851e4","session_id":"ab9d1005-807f-44db-88a9-2f21591500b8","timestamp":"2025-03-15T04:55:37.749Z","type":"lifecycle_view_controller","lifecycle_view_controller":{"type":"viewDidAppear","class_name":"UINavigationController"},"attribute":{"thread_name":"com.apple.main-thread","device_name":"iPhone 16 Pro","device_model":"Simulator iPhone17,1","device_manufacturer":"Apple","device_type":"phone","device_is_foldable":false,"device_is_physical":false,"device_density_dpi":480,"device_width_px":1206,"device_height_px":2622,"device_density":3,"device_locale":"en_IN","os_name":"iOS","os_version":"18.3.1","platform":"ios","network_type":"wifi","network_generation":"unknown","network_provider":"unknown","installation_id":"98aa4d46-a856-45a9-b521-f4566532b572","user_id":"test_user_ios","device_cpu_arch":"arm64e","app_version":"1.0","app_build":"1","measure_sdk_version":"0.0.1","device_low_power_mode":false,"app_unique_id":"sh.measure.DemoApp"},"user_triggered":false},{"id":"9a48eb1c-5156-4674-b98e-a02566eb2240","session_id":"ab9d1005-807f-44db-88a9-2f21591500b8","timestamp":"2025-03-15T04:55:37.753Z","type":"lifecycle_view_controller","lifecycle_view_controller":{"type":"viewDidAppear","class_name":"ViewController"},"attribute":{"thread_name":"com.apple.main-thread","device_name":"iPhone 16 Pro","device_model":"Simulator iPhone17,1","device_manufacturer":"Apple","device_type":"phone","device_is_foldable":false,"device_is_physical":false,"device_density_dpi":480,"device_width_px":1206,"device_height_px":2622,"device_density":3,"device_locale":"en_IN","os_name":"iOS","os_version":"18.3.1","platform":"ios","network_type":"wifi","network_generation":"unknown","network_provider":"unknown","installation_id":"98aa4d46-a856-45a9-b521-f4566532b572","user_id":"test_user_ios","device_cpu_arch":"arm64e","app_version":"1.0","app_build":"1","measure_sdk_version":"0.0.1","device_low_power_mode":false,"app_unique_id":"sh.measure.DemoApp"},"user_triggered":false},{"id":"0da8b710-0746-4d36-8dd2-d2bea015e8f8","session_id":"ab9d1005-807f-44db-88a9-2f21591500b8","timestamp":"2025-03-15T04:55:37.756Z","type":"screen_view","screen_view":{"name":"Home"},"attribute":{"thread_name":"com.apple.main-thread","device_name":"iPhone 16 Pro","device_model":"Simulator iPhone17,1","device_manufacturer":"Apple","device_type":"phone","device_is_foldable":false,"device_is_physical":false,"device_density_dpi":480,"device_width_px":1206,"device_height_px":2622,"device_density":3,"device_locale":"en_IN","os_name":"iOS","os_version":"18.3.1","platform":"ios","network_type":"wifi","network_generation":"unknown","network_provider":"unknown","installation_id":"98aa4d46-a856-45a9-b521-f4566532b572","user_id":"test_user_ios","device_cpu_arch":"arm64e","app_version":"1.0","app_build":"1","measure_sdk_version":"0.0.1","device_low_power_mode":false,"app_unique_id":"sh.measure.DemoApp"},"user_triggered":true},{"id":"40324405-b425-4be2-a345-8c7b61d9f98a","session_id":"ab9d1005-807f-44db-88a9-2f21591500b8","timestamp":"2025-03-15T04:55:37.785Z","type":"warm_launch","warm_launch":{"app_visible_uptime":1742014537000,"on_next_draw_uptime":1742014537785,"launched_activity":"UINavigationController","has_saved_state":false,"intent_data":""},"attribute":{"thread_name":"com.apple.main-thread","device_name":"iPhone 16 Pro","device_model":"Simulator iPhone17,1","device_manufacturer":"Apple","device_type":"phone","device_is_foldable":false,"device_is_physical":false,"device_density_dpi":480,"device_width_px":1206,"device_height_px":2622,"device_density":3,"device_locale":"en_IN","os_name":"iOS","os_version":"18.3.1","platform":"ios","network_type":"wifi","network_generation":"unknown","network_provider":"unknown","installation_id":"98aa4d46-a856-45a9-b521-f4566532b572","user_id":"test_user_ios","device_cpu_arch":"arm64e","app_version":"1.0","app_build":"1","measure_sdk_version":"0.0.1","device_low_power_mode":false,"app_unique_id":"sh.measure.DemoApp"},"user_triggered":false},{"id":"a9b1b73c-0c6a-477f-87d1-e13c048bb1f4","session_id":"ab9d1005-807f-44db-88a9-2f21591500b8","timestamp":"2025-03-15T04:55:44.185Z","type":"lifecycle_view_controller","lifecycle_view_controller":{"type":"viewDidLoad","class_name":"CollectionViewController"},"attribute":{"thread_name":"com.apple.main-thread","device_name":"iPhone 16 Pro","device_model":"Simulator iPhone17,1","device_manufacturer":"Apple","device_type":"phone","device_is_foldable":false,"device_is_physical":false,"device_density_dpi":480,"device_width_px":1206,"device_height_px":2622,"device_density":3,"device_locale":"en_IN","os_name":"iOS","os_version":"18.3.1","platform":"ios","network_type":"wifi","network_generation":"unknown","network_provider":"unknown","installation_id":"98aa4d46-a856-45a9-b521-f4566532b572","user_id":"test_user_ios","device_cpu_arch":"arm64e","app_version":"1.0","app_build":"1","measure_sdk_version":"0.0.1","device_low_power_mode":false,"app_unique_id":"sh.measure.DemoApp"},"user_triggered":false},{"id":"1f90f76d-f8f2-4b63-a839-35aeecb63eed","session_id":"ab9d1005-807f-44db-88a9-2f21591500b8","timestamp":"2025-03-15T04:55:44.198Z","type":"lifecycle_view_controller","lifecycle_view_controller":{"type":"viewWillDisappear","class_name":"ViewController"},"attribute":{"thread_name":"com.apple.main-thread","device_name":"iPhone 16 Pro","device_model":"Simulator iPhone17,1","device_manufacturer":"Apple","device_type":"phone","device_is_foldable":false,"device_is_physical":false,"device_density_dpi":480,"device_width_px":1206,"device_height_px":2622,"device_density":3,"device_locale":"en_IN","os_name":"iOS","os_version":"18.3.1","platform":"ios","network_type":"wifi","network_generation":"unknown","network_provider":"unknown","installation_id":"98aa4d46-a856-45a9-b521-f4566532b572","user_id":"test_user_ios","device_cpu_arch":"arm64e","app_version":"1.0","app_build":"1","measure_sdk_version":"0.0.1","device_low_power_mode":false,"app_unique_id":"sh.measure.DemoApp"},"user_triggered":false},{"id":"6f744c8d-4cea-4d1b-a639-f37ba962e60b","session_id":"ab9d1005-807f-44db-88a9-2f21591500b8","timestamp":"2025-03-15T04:55:44.201Z","type":"lifecycle_view_controller","lifecycle_view_controller":{"type":"viewWillAppear","class_name":"CollectionViewController"},"attribute":{"thread_name":"com.apple.main-thread","device_name":"iPhone 16 Pro","device_model":"Simulator iPhone17,1","device_manufacturer":"Apple","device_type":"phone","device_is_foldable":false,"device_is_physical":false,"device_density_dpi":480,"device_width_px":1206,"device_height_px":2622,"device_density":3,"device_locale":"en_IN","os_name":"iOS","os_version":"18.3.1","platform":"ios","network_type":"wifi","network_generation":"unknown","network_provider":"unknown","installation_id":"98aa4d46-a856-45a9-b521-f4566532b572","user_id":"test_user_ios","device_cpu_arch":"arm64e","app_version":"1.0","app_build":"1","measure_sdk_version":"0.0.1","device_low_power_mode":false,"app_unique_id":"sh.measure.DemoApp"},"user_triggered":false},{"id":"bf063975-6684-4924-8400-9fbb97708cbf","session_id":"ab9d1005-807f-44db-88a9-2f21591500b8","timestamp":"2025-03-15T04:55:44.815Z","type":"lifecycle_view_controller","lifecycle_view_controller":{"type":"viewDidDisappear","class_name":"ViewController"},"attribute":{"thread_name":"com.apple.main-thread","device_name":"iPhone 16 Pro","device_model":"Simulator iPhone17,1","device_manufacturer":"Apple","device_type":"phone","device_is_foldable":false,"device_is_physical":false,"device_density_dpi":480,"device_width_px":1206,"device_height_px":2622,"device_density":3,"device_locale":"en_IN","os_name":"iOS","os_version":"18.3.1","platform":"ios","network_type":"wifi","network_generation":"unknown","network_provider":"unknown","installation_id":"98aa4d46-a856-45a9-b521-f4566532b572","user_id":"test_user_ios","device_cpu_arch":"arm64e","app_version":"1.0","app_build":"1","measure_sdk_version":"0.0.1","device_low_power_mode":false,"app_unique_id":"sh.measure.DemoApp"},"user_triggered":false},{"id":"840fbfc4-6d1d-4fc6-a7eb-77ed2569a6a7","session_id":"ab9d1005-807f-44db-88a9-2f21591500b8","timestamp":"2025-03-15T04:55:44.829Z","type":"lifecycle_view_controller","lifecycle_view_controller":{"type":"viewDidAppear","class_name":"CollectionViewController"},"attribute":{"thread_name":"com.apple.main-thread","device_name":"iPhone 16 Pro","device_model":"Simulator iPhone17,1","device_manufacturer":"Apple","device_type":"phone","device_is_foldable":false,"device_is_physical":false,"device_density_dpi":480,"device_width_px":1206,"device_height_px":2622,"device_density":3,"device_locale":"en_IN","os_name":"iOS","os_version":"18.3.1","platform":"ios","network_type":"wifi","network_generation":"unknown","network_provider":"unknown","installation_id":"98aa4d46-a856-45a9-b521-f4566532b572","user_id":"test_user_ios","device_cpu_arch":"arm64e","app_version":"1.0","app_build":"1","measure_sdk_version":"0.0.1","device_low_power_mode":false,"app_unique_id":"sh.measure.DemoApp"},"user_triggered":false},{"id":"95bb05da-a0a8-40cb-b958-bda995d18308","session_id":"ab9d1005-807f-44db-88a9-2f21591500b8","timestamp":"2025-03-15T04:55:51.281Z","type":"lifecycle_view_controller","lifecycle_view_controller":{"type":"viewWillDisappear","class_name":"CollectionViewController"},"attribute":{"thread_name":"com.apple.main-thread","device_name":"iPhone 16 Pro","device_model":"Simulator iPhone17,1","device_manufacturer":"Apple","device_type":"phone","device_is_foldable":false,"device_is_physical":false,"device_density_dpi":480,"device_width_px":1206,"device_height_px":2622,"device_density":3,"device_locale":"en_IN","os_name":"iOS","os_version":"18.3.1","platform":"ios","network_type":"wifi","network_generation":"unknown","network_provider":"unknown","installation_id":"98aa4d46-a856-45a9-b521-f4566532b572","user_id":"test_user_ios","device_cpu_arch":"arm64e","app_version":"1.0","app_build":"1","measure_sdk_version":"0.0.1","device_low_power_mode":false,"app_unique_id":"sh.measure.DemoApp"},"user_triggered":false},{"id":"5cac46a2-95bd-4631-b185-6c79dd888603","session_id":"ab9d1005-807f-44db-88a9-2f21591500b8","timestamp":"2025-03-15T04:55:51.283Z","type":"lifecycle_view_controller","lifecycle_view_controller":{"type":"viewWillAppear","class_name":"ViewController"},"attribute":{"thread_name":"com.apple.main-thread","device_name":"iPhone 16 Pro","device_model":"Simulator iPhone17,1","device_manufacturer":"Apple","device_type":"phone","device_is_foldable":false,"device_is_physical":false,"device_density_dpi":480,"device_width_px":1206,"device_height_px":2622,"device_density":3,"device_locale":"en_IN","os_name":"iOS","os_version":"18.3.1","platform":"ios","network_type":"wifi","network_generation":"unknown","network_provider":"unknown","installation_id":"98aa4d46-a856-45a9-b521-f4566532b572","user_id":"test_user_ios","device_cpu_arch":"arm64e","app_version":"1.0","app_build":"1","measure_sdk_version":"0.0.1","device_low_power_mode":false,"app_unique_id":"sh.measure.DemoApp"},"user_triggered":false},{"id":"d3cb56b2-29c2-4693-8646-e2a2289feb6b","session_id":"ab9d1005-807f-44db-88a9-2f21591500b8","timestamp":"2025-03-15T04:55:51.809Z","type":"lifecycle_view_controller","lifecycle_view_controller":{"type":"viewDidDisappear","class_name":"CollectionViewController"},"attribute":{"thread_name":"com.apple.main-thread","device_name":"iPhone 16 Pro","device_model":"Simulator iPhone17,1","device_manufacturer":"Apple","device_type":"phone","device_is_foldable":false,"device_is_physical":false,"device_density_dpi":480,"device_width_px":1206,"device_height_px":2622,"device_density":3,"device_locale":"en_IN","os_name":"iOS","os_version":"18.3.1","platform":"ios","network_type":"wifi","network_generation":"unknown","network_provider":"unknown","installation_id":"98aa4d46-a856-45a9-b521-f4566532b572","user_id":"test_user_ios","device_cpu_arch":"arm64e","app_version":"1.0","app_build":"1","measure_sdk_version":"0.0.1","device_low_power_mode":false,"app_unique_id":"sh.measure.DemoApp"},"user_triggered":false},{"id":"89dd22b6-19e2-4cfe-a610-dd6af5a165db","session_id":"ab9d1005-807f-44db-88a9-2f21591500b8","timestamp":"2025-03-15T04:55:51.817Z","type":"lifecycle_view_controller","lifecycle_view_controller":{"type":"viewDidAppear","class_name":"ViewController"},"attribute":{"thread_name":"com.apple.main-thread","device_name":"iPhone 16 Pro","device_model":"Simulator iPhone17,1","device_manufacturer":"Apple","device_type":"phone","device_is_foldable":false,"device_is_physical":false,"device_density_dpi":480,"device_width_px":1206,"device_height_px":2622,"device_density":3,"device_locale":"en_IN","os_name":"iOS","os_version":"18.3.1","platform":"ios","network_type":"wifi","network_generation":"unknown","network_provider":"unknown","installation_id":"98aa4d46-a856-45a9-b521-f4566532b572","user_id":"test_user_ios","device_cpu_arch":"arm64e","app_version":"1.0","app_build":"1","measure_sdk_version":"0.0.1","device_low_power_mode":false,"app_unique_id":"sh.measure.DemoApp"},"user_triggered":false},{"id":"31f12ddc-a44d-479f-86e1-bb3027b83bb9","session_id":"ab9d1005-807f-44db-88a9-2f21591500b8","timestamp":"2025-03-15T04:55:51.821Z","type":"screen_view","screen_view":{"name":"Home"},"attribute":{"thread_name":"com.apple.main-thread","device_name":"iPhone 16 Pro","device_model":"Simulator iPhone17,1","device_manufacturer":"Apple","device_type":"phone","device_is_foldable":false,"device_is_physical":false,"device_density_dpi":480,"device_width_px":1206,"device_height_px":2622,"device_density":3,"device_locale":"en_IN","os_name":"iOS","os_version":"18.3.1","platform":"ios","network_type":"wifi","network_generation":"unknown","network_provider":"unknown","installation_id":"98aa4d46-a856-45a9-b521-f4566532b572","user_id":"test_user_ios","device_cpu_arch":"arm64e","app_version":"1.0","app_build":"1","measure_sdk_version":"0.0.1","device_low_power_mode":false,"app_unique_id":"sh.measure.DemoApp"},"user_triggered":true},{"id":"5cb9a8da-f8e0-410f-aea0-dec006d42da4","session_id":"ab9d1005-807f-44db-88a9-2f21591500b8","timestamp":"2025-03-15T04:55:54.105Z","type":"lifecycle_view_controller","lifecycle_view_controller":{"type":"viewDidLoad","class_name":"ControlsViewController"},"attribute":{"thread_name":"com.apple.main-thread","device_name":"iPhone 16 Pro","device_model":"Simulator iPhone17,1","device_manufacturer":"Apple","device_type":"phone","device_is_foldable":false,"device_is_physical":false,"device_density_dpi":480,"device_width_px":1206,"device_height_px":2622,"device_density":3,"device_locale":"en_IN","os_name":"iOS","os_version":"18.3.1","platform":"ios","network_type":"wifi","network_generation":"unknown","network_provider":"unknown","installation_id":"98aa4d46-a856-45a9-b521-f4566532b572","user_id":"test_user_ios","device_cpu_arch":"arm64e","app_version":"1.0","app_build":"1","measure_sdk_version":"0.0.1","device_low_power_mode":false,"app_unique_id":"sh.measure.DemoApp"},"user_triggered":false},{"id":"9988f79d-d8ed-455b-9de0-351bde43d6c8","session_id":"ab9d1005-807f-44db-88a9-2f21591500b8","timestamp":"2025-03-15T04:55:54.108Z","type":"lifecycle_view_controller","lifecycle_view_controller":{"type":"viewWillDisappear","class_name":"ViewController"},"attribute":{"thread_name":"com.apple.main-thread","device_name":"iPhone 16 Pro","device_model":"Simulator iPhone17,1","device_manufacturer":"Apple","device_type":"phone","device_is_foldable":false,"device_is_physical":false,"device_density_dpi":480,"device_width_px":1206,"device_height_px":2622,"device_density":3,"device_locale":"en_IN","os_name":"iOS","os_version":"18.3.1","platform":"ios","network_type":"wifi","network_generation":"unknown","network_provider":"unknown","installation_id":"98aa4d46-a856-45a9-b521-f4566532b572","user_id":"test_user_ios","device_cpu_arch":"arm64e","app_version":"1.0","app_build":"1","measure_sdk_version":"0.0.1","device_low_power_mode":false,"app_unique_id":"sh.measure.DemoApp"},"user_triggered":false},{"id":"a4a902d6-79f5-4d41-a191-c169f5e9ad00","session_id":"ab9d1005-807f-44db-88a9-2f21591500b8","timestamp":"2025-03-15T04:55:54.111Z","type":"lifecycle_view_controller","lifecycle_view_controller":{"type":"viewWillAppear","class_name":"ControlsViewController"},"attribute":{"thread_name":"com.apple.main-thread","device_name":"iPhone 16 Pro","device_model":"Simulator iPhone17,1","device_manufacturer":"Apple","device_type":"phone","device_is_foldable":false,"device_is_physical":false,"device_density_dpi":480,"device_width_px":1206,"device_height_px":2622,"device_density":3,"device_locale":"en_IN","os_name":"iOS","os_version":"18.3.1","platform":"ios","network_type":"wifi","network_generation":"unknown","network_provider":"unknown","installation_id":"98aa4d46-a856-45a9-b521-f4566532b572","user_id":"test_user_ios","device_cpu_arch":"arm64e","app_version":"1.0","app_build":"1","measure_sdk_version":"0.0.1","device_low_power_mode":false,"app_unique_id":"sh.measure.DemoApp"},"user_triggered":false},{"id":"0faa3e28-1e0b-4c25-9f70-5ef62adc1ca4","session_id":"ab9d1005-807f-44db-88a9-2f21591500b8","timestamp":"2025-03-15T04:55:54.632Z","type":"lifecycle_view_controller","lifecycle_view_controller":{"type":"viewDidDisappear","class_name":"ViewController"},"attribute":{"thread_name":"com.apple.main-thread","device_name":"iPhone 16 Pro","device_model":"Simulator iPhone17,1","device_manufacturer":"Apple","device_type":"phone","device_is_foldable":false,"device_is_physical":false,"device_density_dpi":480,"device_width_px":1206,"device_height_px":2622,"device_density":3,"device_locale":"en_IN","os_name":"iOS","os_version":"18.3.1","platform":"ios","network_type":"wifi","network_generation":"unknown","network_provider":"unknown","installation_id":"98aa4d46-a856-45a9-b521-f4566532b572","user_id":"test_user_ios","device_cpu_arch":"arm64e","app_version":"1.0","app_build":"1","measure_sdk_version":"0.0.1","device_low_power_mode":false,"app_unique_id":"sh.measure.DemoApp"},"user_triggered":false},{"id":"634387a0-6784-40b7-8b16-638d2430e72a","session_id":"ab9d1005-807f-44db-88a9-2f21591500b8","timestamp":"2025-03-15T04:55:54.643Z","type":"lifecycle_view_controller","lifecycle_view_controller":{"type":"viewDidAppear","class_name":"ControlsViewController"},"attribute":{"thread_name":"com.apple.main-thread","device_name":"iPhone 16 Pro","device_model":"Simulator iPhone17,1","device_manufacturer":"Apple","device_type":"phone","device_is_foldable":false,"device_is_physical":false,"device_density_dpi":480,"device_width_px":1206,"device_height_px":2622,"device_density":3,"device_locale":"en_IN","os_name":"iOS","os_version":"18.3.1","platform":"ios","network_type":"wifi","network_generation":"unknown","network_provider":"unknown","installation_id":"98aa4d46-a856-45a9-b521-f4566532b572","user_id":"test_user_ios","device_cpu_arch":"arm64e","app_version":"1.0","app_build":"1","measure_sdk_version":"0.0.1","device_low_power_mode":false,"app_unique_id":"sh.measure.DemoApp"},"user_triggered":false},{"id":"e7d626af-251e-461a-b03d-deab9cfcb409","session_id":"ab9d1005-807f-44db-88a9-2f21591500b8","timestamp":"2025-03-15T04:55:56.003Z","type":"lifecycle_view_controller","lifecycle_view_controller":{"type":"viewDidLoad","class_name":"_UIAlertControllerTextFieldViewController"},"attribute":{"thread_name":"com.apple.main-thread","device_name":"iPhone 16 Pro","device_model":"Simulator iPhone17,1","device_manufacturer":"Apple","device_type":"phone","device_is_foldable":false,"device_is_physical":false,"device_density_dpi":480,"device_width_px":1206,"device_height_px":2622,"device_density":3,"device_locale":"en_IN","os_name":"iOS","os_version":"18.3.1","platform":"ios","network_type":"wifi","network_generation":"unknown","network_provider":"unknown","installation_id":"98aa4d46-a856-45a9-b521-f4566532b572","user_id":"test_user_ios","device_cpu_arch":"arm64e","app_version":"1.0","app_build":"1","measure_sdk_version":"0.0.1","device_low_power_mode":false,"app_unique_id":"sh.measure.DemoApp"},"user_triggered":false},{"id":"30ae0fdc-1307-467b-b121-2f4d3b83a6b4","session_id":"ab9d1005-807f-44db-88a9-2f21591500b8","timestamp":"2025-03-15T04:55:56.020Z","type":"lifecycle_view_controller","lifecycle_view_controller":{"type":"viewDidLoad","class_name":"UIAlertController"},"attribute":{"thread_name":"com.apple.main-thread","device_name":"iPhone 16 Pro","device_model":"Simulator iPhone17,1","device_manufacturer":"Apple","device_type":"phone","device_is_foldable":false,"device_is_physical":false,"device_density_dpi":480,"device_width_px":1206,"device_height_px":2622,"device_density":3,"device_locale":"en_IN","os_name":"iOS","os_version":"18.3.1","platform":"ios","network_type":"wifi","network_generation":"unknown","network_provider":"unknown","installation_id":"98aa4d46-a856-45a9-b521-f4566532b572","user_id":"test_user_ios","device_cpu_arch":"arm64e","app_version":"1.0","app_build":"1","measure_sdk_version":"0.0.1","device_low_power_mode":false,"app_unique_id":"sh.measure.DemoApp"},"user_triggered":false},{"id":"a158bf3f-d8c4-4316-bd74-09b0e680c802","session_id":"ab9d1005-807f-44db-88a9-2f21591500b8","timestamp":"2025-03-15T04:55:56.073Z","type":"lifecycle_view_controller","lifecycle_view_controller":{"type":"viewDidLoad","class_name":"UIInputWindowController"},"attribute":{"thread_name":"com.apple.main-thread","device_name":"iPhone 16 Pro","device_model":"Simulator iPhone17,1","device_manufacturer":"Apple","device_type":"phone","device_is_foldable":false,"device_is_physical":false,"device_density_dpi":480,"device_width_px":1206,"device_height_px":2622,"device_density":3,"device_locale":"en_IN","os_name":"iOS","os_version":"18.3.1","platform":"ios","network_type":"wifi","network_generation":"unknown","network_provider":"unknown","installation_id":"98aa4d46-a856-45a9-b521-f4566532b572","user_id":"test_user_ios","device_cpu_arch":"arm64e","app_version":"1.0","app_build":"1","measure_sdk_version":"0.0.1","device_low_power_mode":false,"app_unique_id":"sh.measure.DemoApp"},"user_triggered":false},{"id":"aa09a979-21cf-4c09-aa0f-a1938e2705dd","session_id":"ab9d1005-807f-44db-88a9-2f21591500b8","timestamp":"2025-03-15T04:55:56.078Z","type":"lifecycle_view_controller","lifecycle_view_controller":{"type":"viewWillAppear","class_name":"UIInputWindowController"},"attribute":{"thread_name":"com.apple.main-thread","device_name":"iPhone 16 Pro","device_model":"Simulator iPhone17,1","device_manufacturer":"Apple","device_type":"phone","device_is_foldable":false,"device_is_physical":false,"device_density_dpi":480,"device_width_px":1206,"device_height_px":2622,"device_density":3,"device_locale":"en_IN","os_name":"iOS","os_version":"18.3.1","platform":"ios","network_type":"wifi","network_generation":"unknown","network_provider":"unknown","installation_id":"98aa4d46-a856-45a9-b521-f4566532b572","user_id":"test_user_ios","device_cpu_arch":"arm64e","app_version":"1.0","app_build":"1","measure_sdk_version":"0.0.1","device_low_power_mode":false,"app_unique_id":"sh.measure.DemoApp"},"user_triggered":false},{"id":"dc752575-e5f0-404d-a430-2f29046f8cb8","session_id":"ab9d1005-807f-44db-88a9-2f21591500b8","timestamp":"2025-03-15T04:55:56.083Z","type":"lifecycle_view_controller","lifecycle_view_controller":{"type":"viewDidLoad","class_name":"UIEditingOverlayViewController"},"attribute":{"thread_name":"com.apple.main-thread","device_name":"iPhone 16 Pro","device_model":"Simulator iPhone17,1","device_manufacturer":"Apple","device_type":"phone","device_is_foldable":false,"device_is_physical":false,"device_density_dpi":480,"device_width_px":1206,"device_height_px":2622,"device_density":3,"device_locale":"en_IN","os_name":"iOS","os_version":"18.3.1","platform":"ios","network_type":"wifi","network_generation":"unknown","network_provider":"unknown","installation_id":"98aa4d46-a856-45a9-b521-f4566532b572","user_id":"test_user_ios","device_cpu_arch":"arm64e","app_version":"1.0","app_build":"1","measure_sdk_version":"0.0.1","device_low_power_mode":false,"app_unique_id":"sh.measure.DemoApp"},"user_triggered":false},{"id":"7e8b8731-ac87-4de6-a578-3bf782bd3dce","session_id":"ab9d1005-807f-44db-88a9-2f21591500b8","timestamp":"2025-03-15T04:55:56.084Z","type":"lifecycle_view_controller","lifecycle_view_controller":{"type":"viewWillAppear","class_name":"UIEditingOverlayViewController"},"attribute":{"thread_name":"com.apple.main-thread","device_name":"iPhone 16 Pro","device_model":"Simulator iPhone17,1","device_manufacturer":"Apple","device_type":"phone","device_is_foldable":false,"device_is_physical":false,"device_density_dpi":480,"device_width_px":1206,"device_height_px":2622,"device_density":3,"device_locale":"en_IN","os_name":"iOS","os_version":"18.3.1","platform":"ios","network_type":"wifi","network_generation":"unknown","network_provider":"unknown","installation_id":"98aa4d46-a856-45a9-b521-f4566532b572","user_id":"test_user_ios","device_cpu_arch":"arm64e","app_version":"1.0","app_build":"1","measure_sdk_version":"0.0.1","device_low_power_mode":false,"app_unique_id":"sh.measure.DemoApp"},"user_triggered":false},{"id":"cb99c01b-6a1a-4915-8053-d4eed6f42730","session_id":"ab9d1005-807f-44db-88a9-2f21591500b8","timestamp":"2025-03-15T04:55:56.087Z","type":"lifecycle_view_controller","lifecycle_view_controller":{"type":"viewWillAppear","class_name":"UIAlertController"},"attribute":{"thread_name":"com.apple.main-thread","device_name":"iPhone 16 Pro","device_model":"Simulator iPhone17,1","device_manufacturer":"Apple","device_type":"phone","device_is_foldable":false,"device_is_physical":false,"device_density_dpi":480,"device_width_px":1206,"device_height_px":2622,"device_density":3,"device_locale":"en_IN","os_name":"iOS","os_version":"18.3.1","platform":"ios","network_type":"wifi","network_generation":"unknown","network_provider":"unknown","installation_id":"98aa4d46-a856-45a9-b521-f4566532b572","user_id":"test_user_ios","device_cpu_arch":"arm64e","app_version":"1.0","app_build":"1","measure_sdk_version":"0.0.1","device_low_power_mode":false,"app_unique_id":"sh.measure.DemoApp"},"user_triggered":false},{"id":"b676c228-0224-4d62-b7b2-aec860ad05ba","session_id":"ab9d1005-807f-44db-88a9-2f21591500b8","timestamp":"2025-03-15T04:55:56.092Z","type":"lifecycle_view_controller","lifecycle_view_controller":{"type":"viewDidAppear","class_name":"UIInputWindowController"},"attribute":{"thread_name":"com.apple.main-thread","device_name":"iPhone 16 Pro","device_model":"Simulator iPhone17,1","device_manufacturer":"Apple","device_type":"phone","device_is_foldable":false,"device_is_physical":false,"device_density_dpi":480,"device_width_px":1206,"device_height_px":2622,"device_density":3,"device_locale":"en_IN","os_name":"iOS","os_version":"18.3.1","platform":"ios","network_type":"wifi","network_generation":"unknown","network_provider":"unknown","installation_id":"98aa4d46-a856-45a9-b521-f4566532b572","user_id":"test_user_ios","device_cpu_arch":"arm64e","app_version":"1.0","app_build":"1","measure_sdk_version":"0.0.1","device_low_power_mode":false,"app_unique_id":"sh.measure.DemoApp"},"user_triggered":false},{"id":"082edcad-17f3-4f1d-8265-bde5849a898e","session_id":"ab9d1005-807f-44db-88a9-2f21591500b8","timestamp":"2025-03-15T04:55:56.499Z","type":"lifecycle_view_controller","lifecycle_view_controller":{"type":"viewDidAppear","class_name":"UIAlertController"},"attribute":{"thread_name":"com.apple.main-thread","device_name":"iPhone 16 Pro","device_model":"Simulator iPhone17,1","device_manufacturer":"Apple","device_type":"phone","device_is_foldable":false,"device_is_physical":false,"device_density_dpi":480,"device_width_px":1206,"device_height_px":2622,"device_density":3,"device_locale":"en_IN","os_name":"iOS","os_version":"18.3.1","platform":"ios","network_type":"wifi","network_generation":"unknown","network_provider":"unknown","installation_id":"98aa4d46-a856-45a9-b521-f4566532b572","user_id":"test_user_ios","device_cpu_arch":"arm64e","app_version":"1.0","app_build":"1","measure_sdk_version":"0.0.1","device_low_power_mode":false,"app_unique_id":"sh.measure.DemoApp"},"user_triggered":false},{"id":"e4bbda5b-8214-4d43-b71b-19230d2c874b","session_id":"ab9d1005-807f-44db-88a9-2f21591500b8","timestamp":"2025-03-15T04:55:57.179Z","type":"lifecycle_view_controller","lifecycle_view_controller":{"type":"viewWillDisappear","class_name":"UIAlertController"},"attribute":{"thread_name":"com.apple.main-thread","device_name":"iPhone 16 Pro","device_model":"Simulator iPhone17,1","device_manufacturer":"Apple","device_type":"phone","device_is_foldable":false,"device_is_physical":false,"device_density_dpi":480,"device_width_px":1206,"device_height_px":2622,"device_density":3,"device_locale":"en_IN","os_name":"iOS","os_version":"18.3.1","platform":"ios","network_type":"wifi","network_generation":"unknown","network_provider":"unknown","installation_id":"98aa4d46-a856-45a9-b521-f4566532b572","user_id":"test_user_ios","device_cpu_arch":"arm64e","app_version":"1.0","app_build":"1","measure_sdk_version":"0.0.1","device_low_power_mode":false,"app_unique_id":"sh.measure.DemoApp"},"user_triggered":false},{"id":"8855d8d4-5bfe-4d89-be65-1c02610abc76","session_id":"ab9d1005-807f-44db-88a9-2f21591500b8","timestamp":"2025-03-15T04:55:57.600Z","type":"lifecycle_view_controller","lifecycle_view_controller":{"type":"viewDidDisappear","class_name":"UIAlertController"},"attribute":{"thread_name":"com.apple.main-thread","device_name":"iPhone 16 Pro","device_model":"Simulator iPhone17,1","device_manufacturer":"Apple","device_type":"phone","device_is_foldable":false,"device_is_physical":false,"device_density_dpi":480,"device_width_px":1206,"device_height_px":2622,"device_density":3,"device_locale":"en_IN","os_name":"iOS","os_version":"18.3.1","platform":"ios","network_type":"wifi","network_generation":"unknown","network_provider":"unknown","installation_id":"98aa4d46-a856-45a9-b521-f4566532b572","user_id":"test_user_ios","device_cpu_arch":"arm64e","app_version":"1.0","app_build":"1","measure_sdk_version":"0.0.1","device_low_power_mode":false,"app_unique_id":"sh.measure.DemoApp"},"user_triggered":false},{"id":"9329804f-36ca-4cdd-a1e9-a70b179ed78f","session_id":"ab9d1005-807f-44db-88a9-2f21591500b8","timestamp":"2025-03-15T04:55:58.166Z","type":"lifecycle_view_controller","lifecycle_view_controller":{"type":"viewWillDisappear","class_name":"ControlsViewController"},"attribute":{"thread_name":"com.apple.main-thread","device_name":"iPhone 16 Pro","device_model":"Simulator iPhone17,1","device_manufacturer":"Apple","device_type":"phone","device_is_foldable":false,"device_is_physical":false,"device_density_dpi":480,"device_width_px":1206,"device_height_px":2622,"device_density":3,"device_locale":"en_IN","os_name":"iOS","os_version":"18.3.1","platform":"ios","network_type":"wifi","network_generation":"unknown","network_provider":"unknown","installation_id":"98aa4d46-a856-45a9-b521-f4566532b572","user_id":"test_user_ios","device_cpu_arch":"arm64e","app_version":"1.0","app_build":"1","measure_sdk_version":"0.0.1","device_low_power_mode":false,"app_unique_id":"sh.measure.DemoApp"},"user_triggered":false},{"id":"b4ff3072-1dd8-4ee4-9598-40448a2b5778","session_id":"ab9d1005-807f-44db-88a9-2f21591500b8","timestamp":"2025-03-15T04:55:58.169Z","type":"lifecycle_view_controller","lifecycle_view_controller":{"type":"viewWillAppear","class_name":"ViewController"},"attribute":{"thread_name":"com.apple.main-thread","device_name":"iPhone 16 Pro","device_model":"Simulator iPhone17,1","device_manufacturer":"Apple","device_type":"phone","device_is_foldable":false,"device_is_physical":false,"device_density_dpi":480,"device_width_px":1206,"device_height_px":2622,"device_density":3,"device_locale":"en_IN","os_name":"iOS","os_version":"18.3.1","platform":"ios","network_type":"wifi","network_generation":"unknown","network_provider":"unknown","installation_id":"98aa4d46-a856-45a9-b521-f4566532b572","user_id":"test_user_ios","device_cpu_arch":"arm64e","app_version":"1.0","app_build":"1","measure_sdk_version":"0.0.1","device_low_power_mode":false,"app_unique_id":"sh.measure.DemoApp"},"user_triggered":false},{"id":"3cfb89e6-0f2c-47bf-a5e5-c48ee4e959e3","session_id":"ab9d1005-807f-44db-88a9-2f21591500b8","timestamp":"2025-03-15T04:55:58.685Z","type":"lifecycle_view_controller","lifecycle_view_controller":{"type":"viewDidDisappear","class_name":"ControlsViewController"},"attribute":{"thread_name":"com.apple.main-thread","device_name":"iPhone 16 Pro","device_model":"Simulator iPhone17,1","device_manufacturer":"Apple","device_type":"phone","device_is_foldable":false,"device_is_physical":false,"device_density_dpi":480,"device_width_px":1206,"device_height_px":2622,"device_density":3,"device_locale":"en_IN","os_name":"iOS","os_version":"18.3.1","platform":"ios","network_type":"wifi","network_generation":"unknown","network_provider":"unknown","installation_id":"98aa4d46-a856-45a9-b521-f4566532b572","user_id":"test_user_ios","device_cpu_arch":"arm64e","app_version":"1.0","app_build":"1","measure_sdk_version":"0.0.1","device_low_power_mode":false,"app_unique_id":"sh.measure.DemoApp"},"user_triggered":false},{"id":"c43f082c-3baf-4419-8d94-3b9a7c90fcdf","session_id":"ab9d1005-807f-44db-88a9-2f21591500b8","timestamp":"2025-03-15T04:55:58.690Z","type":"lifecycle_view_controller","lifecycle_view_controller":{"type":"viewDidAppear","class_name":"ViewController"},"attribute":{"thread_name":"com.apple.main-thread","device_name":"iPhone 16 Pro","device_model":"Simulator iPhone17,1","device_manufacturer":"Apple","device_type":"phone","device_is_foldable":false,"device_is_physical":false,"device_density_dpi":480,"device_width_px":1206,"device_height_px":2622,"device_density":3,"device_locale":"en_IN","os_name":"iOS","os_version":"18.3.1","platform":"ios","network_type":"wifi","network_generation":"unknown","network_provider":"unknown","installation_id":"98aa4d46-a856-45a9-b521-f4566532b572","user_id":"test_user_ios","device_cpu_arch":"arm64e","app_version":"1.0","app_build":"1","measure_sdk_version":"0.0.1","device_low_power_mode":false,"app_unique_id":"sh.measure.DemoApp"},"user_triggered":false},{"id":"118144a3-acf3-4924-ab4e-d94f8e822ec3","session_id":"ab9d1005-807f-44db-88a9-2f21591500b8","timestamp":"2025-03-15T04:55:58.694Z","type":"screen_view","screen_view":{"name":"Home"},"attribute":{"thread_name":"com.apple.main-thread","device_name":"iPhone 16 Pro","device_model":"Simulator iPhone17,1","device_manufacturer":"Apple","device_type":"phone","device_is_foldable":false,"device_is_physical":false,"device_density_dpi":480,"device_width_px":1206,"device_height_px":2622,"device_density":3,"device_locale":"en_IN","os_name":"iOS","os_version":"18.3.1","platform":"ios","network_type":"wifi","network_generation":"unknown","network_provider":"unknown","installation_id":"98aa4d46-a856-45a9-b521-f4566532b572","user_id":"test_user_ios","device_cpu_arch":"arm64e","app_version":"1.0","app_build":"1","measure_sdk_version":"0.0.1","device_low_power_mode":false,"app_unique_id":"sh.measure.DemoApp"},"user_triggered":true},{"id":"88148414-23dd-4ac6-a1bc-a361976e9c44","session_id":"ab9d1005-807f-44db-88a9-2f21591500b8","timestamp":"2025-03-15T04:55:59.261Z","type":"lifecycle_view_controller","lifecycle_view_controller":{"type":"viewDidLoad","class_name":"ObjcDetailViewController"},"attribute":{"thread_name":"com.apple.main-thread","device_name":"iPhone 16 Pro","device_model":"Simulator iPhone17,1","device_manufacturer":"Apple","device_type":"phone","device_is_foldable":false,"device_is_physical":false,"device_density_dpi":480,"device_width_px":1206,"device_height_px":2622,"device_density":3,"device_locale":"en_IN","os_name":"iOS","os_version":"18.3.1","platform":"ios","network_type":"wifi","network_generation":"unknown","network_provider":"unknown","installation_id":"98aa4d46-a856-45a9-b521-f4566532b572","user_id":"test_user_ios","device_cpu_arch":"arm64e","app_version":"1.0","app_build":"1","measure_sdk_version":"0.0.1","device_low_power_mode":false,"app_unique_id":"sh.measure.DemoApp"},"user_triggered":false},{"id":"a5a72a11-cc8a-4a01-b1d7-8d10818b4608","session_id":"ab9d1005-807f-44db-88a9-2f21591500b8","timestamp":"2025-03-15T04:55:59.271Z","type":"screen_view","screen_view":{"name":"ObjcViewController"},"attribute":{"thread_name":"com.apple.main-thread","device_name":"iPhone 16 Pro","device_model":"Simulator iPhone17,1","device_manufacturer":"Apple","device_type":"phone","device_is_foldable":false,"device_is_physical":false,"device_density_dpi":480,"device_width_px":1206,"device_height_px":2622,"device_density":3,"device_locale":"en_IN","os_name":"iOS","os_version":"18.3.1","platform":"ios","network_type":"wifi","network_generation":"unknown","network_provider":"unknown","installation_id":"98aa4d46-a856-45a9-b521-f4566532b572","user_id":"test_user_ios","device_cpu_arch":"arm64e","app_version":"1.0","app_build":"1","measure_sdk_version":"0.0.1","device_low_power_mode":false,"app_unique_id":"sh.measure.DemoApp"},"user_triggered":true},{"id":"da0f1789-267b-47bd-9015-051ca0b1c92e","session_id":"ab9d1005-807f-44db-88a9-2f21591500b8","timestamp":"2025-03-15T04:55:59.274Z","type":"lifecycle_view_controller","lifecycle_view_controller":{"type":"viewWillDisappear","class_name":"ViewController"},"attribute":{"thread_name":"com.apple.main-thread","device_name":"iPhone 16 Pro","device_model":"Simulator iPhone17,1","device_manufacturer":"Apple","device_type":"phone","device_is_foldable":false,"device_is_physical":false,"device_density_dpi":480,"device_width_px":1206,"device_height_px":2622,"device_density":3,"device_locale":"en_IN","os_name":"iOS","os_version":"18.3.1","platform":"ios","network_type":"wifi","network_generation":"unknown","network_provider":"unknown","installation_id":"98aa4d46-a856-45a9-b521-f4566532b572","user_id":"test_user_ios","device_cpu_arch":"arm64e","app_version":"1.0","app_build":"1","measure_sdk_version":"0.0.1","device_low_power_mode":false,"app_unique_id":"sh.measure.DemoApp"},"user_triggered":false},{"id":"5b92a353-04b2-4baf-888c-eb2c79d3e804","session_id":"ab9d1005-807f-44db-88a9-2f21591500b8","timestamp":"2025-03-15T04:55:59.277Z","type":"lifecycle_view_controller","lifecycle_view_controller":{"type":"viewWillAppear","class_name":"ObjcDetailViewController"},"attribute":{"thread_name":"com.apple.main-thread","device_name":"iPhone 16 Pro","device_model":"Simulator iPhone17,1","device_manufacturer":"Apple","device_type":"phone","device_is_foldable":false,"device_is_physical":false,"device_density_dpi":480,"device_width_px":1206,"device_height_px":2622,"device_density":3,"device_locale":"en_IN","os_name":"iOS","os_version":"18.3.1","platform":"ios","network_type":"wifi","network_generation":"unknown","network_provider":"unknown","installation_id":"98aa4d46-a856-45a9-b521-f4566532b572","user_id":"test_user_ios","device_cpu_arch":"arm64e","app_version":"1.0","app_build":"1","measure_sdk_version":"0.0.1","device_low_power_mode":false,"app_unique_id":"sh.measure.DemoApp"},"user_triggered":false},{"id":"56df865e-f79a-4ec1-b0c2-6a59cf57aa6d","session_id":"ab9d1005-807f-44db-88a9-2f21591500b8","timestamp":"2025-03-15T04:55:59.799Z","type":"lifecycle_view_controller","lifecycle_view_controller":{"type":"viewDidDisappear","class_name":"ViewController"},"attribute":{"thread_name":"com.apple.main-thread","device_name":"iPhone 16 Pro","device_model":"Simulator iPhone17,1","device_manufacturer":"Apple","device_type":"phone","device_is_foldable":false,"device_is_physical":false,"device_density_dpi":480,"device_width_px":1206,"device_height_px":2622,"device_density":3,"device_locale":"en_IN","os_name":"iOS","os_version":"18.3.1","platform":"ios","network_type":"wifi","network_generation":"unknown","network_provider":"unknown","installation_id":"98aa4d46-a856-45a9-b521-f4566532b572","user_id":"test_user_ios","device_cpu_arch":"arm64e","app_version":"1.0","app_build":"1","measure_sdk_version":"0.0.1","device_low_power_mode":false,"app_unique_id":"sh.measure.DemoApp"},"user_triggered":false},{"id":"e70d7222-f186-4c68-a670-43ab978a9d3e","session_id":"ab9d1005-807f-44db-88a9-2f21591500b8","timestamp":"2025-03-15T04:55:59.811Z","type":"lifecycle_view_controller","lifecycle_view_controller":{"type":"viewDidAppear","class_name":"ObjcDetailViewController"},"attribute":{"thread_name":"com.apple.main-thread","device_name":"iPhone 16 Pro","device_model":"Simulator iPhone17,1","device_manufacturer":"Apple","device_type":"phone","device_is_foldable":false,"device_is_physical":false,"device_density_dpi":480,"device_width_px":1206,"device_height_px":2622,"device_density":3,"device_locale":"en_IN","os_name":"iOS","os_version":"18.3.1","platform":"ios","network_type":"wifi","network_generation":"unknown","network_provider":"unknown","installation_id":"98aa4d46-a856-45a9-b521-f4566532b572","user_id":"test_user_ios","device_cpu_arch":"arm64e","app_version":"1.0","app_build":"1","measure_sdk_version":"0.0.1","device_low_power_mode":false,"app_unique_id":"sh.measure.DemoApp"},"user_triggered":false},{"id":"6a7e9c77-c5ae-4302-bbbc-7e3e3c1eec71","session_id":"ab9d1005-807f-44db-88a9-2f21591500b8","timestamp":"2025-03-15T04:56:01.250Z","type":"lifecycle_view_controller","lifecycle_view_controller":{"type":"viewDidLoad","class_name":"CollectionViewController"},"attribute":{"thread_name":"com.apple.main-thread","device_name":"iPhone 16 Pro","device_model":"Simulator iPhone17,1","device_manufacturer":"Apple","device_type":"phone","device_is_foldable":false,"device_is_physical":false,"device_density_dpi":480,"device_width_px":1206,"device_height_px":2622,"device_density":3,"device_locale":"en_IN","os_name":"iOS","os_version":"18.3.1","platform":"ios","network_type":"wifi","network_generation":"unknown","network_provider":"unknown","installation_id":"98aa4d46-a856-45a9-b521-f4566532b572","user_id":"test_user_ios","device_cpu_arch":"arm64e","app_version":"1.0","app_build":"1","measure_sdk_version":"0.0.1","device_low_power_mode":false,"app_unique_id":"sh.measure.DemoApp"},"user_triggered":false},{"id":"55608512-260b-4c53-bb73-e3d8c59e515f","session_id":"ab9d1005-807f-44db-88a9-2f21591500b8","timestamp":"2025-03-15T04:56:01.256Z","type":"lifecycle_view_controller","lifecycle_view_controller":{"type":"viewWillDisappear","class_name":"ObjcDetailViewController"},"attribute":{"thread_name":"com.apple.main-thread","device_name":"iPhone 16 Pro","device_model":"Simulator iPhone17,1","device_manufacturer":"Apple","device_type":"phone","device_is_foldable":false,"device_is_physical":false,"device_density_dpi":480,"device_width_px":1206,"device_height_px":2622,"device_density":3,"device_locale":"en_IN","os_name":"iOS","os_version":"18.3.1","platform":"ios","network_type":"wifi","network_generation":"unknown","network_provider":"unknown","installation_id":"98aa4d46-a856-45a9-b521-f4566532b572","user_id":"test_user_ios","device_cpu_arch":"arm64e","app_version":"1.0","app_build":"1","measure_sdk_version":"0.0.1","device_low_power_mode":false,"app_unique_id":"sh.measure.DemoApp"},"user_triggered":false},{"id":"f09ab766-3165-429d-a418-be27afe54b00","session_id":"ab9d1005-807f-44db-88a9-2f21591500b8","timestamp":"2025-03-15T04:56:01.259Z","type":"lifecycle_view_controller","lifecycle_view_controller":{"type":"viewWillAppear","class_name":"CollectionViewController"},"attribute":{"thread_name":"com.apple.main-thread","device_name":"iPhone 16 Pro","device_model":"Simulator iPhone17,1","device_manufacturer":"Apple","device_type":"phone","device_is_foldable":false,"device_is_physical":false,"device_density_dpi":480,"device_width_px":1206,"device_height_px":2622,"device_density":3,"device_locale":"en_IN","os_name":"iOS","os_version":"18.3.1","platform":"ios","network_type":"wifi","network_generation":"unknown","network_provider":"unknown","installation_id":"98aa4d46-a856-45a9-b521-f4566532b572","user_id":"test_user_ios","device_cpu_arch":"arm64e","app_version":"1.0","app_build":"1","measure_sdk_version":"0.0.1","device_low_power_mode":false,"app_unique_id":"sh.measure.DemoApp"},"user_triggered":false},{"id":"7af1e0cb-73ac-418b-b4ee-6d33f67e1205","session_id":"ab9d1005-807f-44db-88a9-2f21591500b8","timestamp":"2025-03-15T04:56:01.790Z","type":"lifecycle_view_controller","lifecycle_view_controller":{"type":"viewDidDisappear","class_name":"ObjcDetailViewController"},"attribute":{"thread_name":"com.apple.main-thread","device_name":"iPhone 16 Pro","device_model":"Simulator iPhone17,1","device_manufacturer":"Apple","device_type":"phone","device_is_foldable":false,"device_is_physical":false,"device_density_dpi":480,"device_width_px":1206,"device_height_px":2622,"device_density":3,"device_locale":"en_IN","os_name":"iOS","os_version":"18.3.1","platform":"ios","network_type":"wifi","network_generation":"unknown","network_provider":"unknown","installation_id":"98aa4d46-a856-45a9-b521-f4566532b572","user_id":"test_user_ios","device_cpu_arch":"arm64e","app_version":"1.0","app_build":"1","measure_sdk_version":"0.0.1","device_low_power_mode":false,"app_unique_id":"sh.measure.DemoApp"},"user_triggered":false},{"id":"4f01710f-d5ab-4b83-9261-254c36edfb97","session_id":"ab9d1005-807f-44db-88a9-2f21591500b8","timestamp":"2025-03-15T04:56:01.799Z","type":"lifecycle_view_controller","lifecycle_view_controller":{"type":"viewDidAppear","class_name":"CollectionViewController"},"attribute":{"thread_name":"com.apple.main-thread","device_name":"iPhone 16 Pro","device_model":"Simulator iPhone17,1","device_manufacturer":"Apple","device_type":"phone","device_is_foldable":false,"device_is_physical":false,"device_density_dpi":480,"device_width_px":1206,"device_height_px":2622,"device_density":3,"device_locale":"en_IN","os_name":"iOS","os_version":"18.3.1","platform":"ios","network_type":"wifi","network_generation":"unknown","network_provider":"unknown","installation_id":"98aa4d46-a856-45a9-b521-f4566532b572","user_id":"test_user_ios","device_cpu_arch":"arm64e","app_version":"1.0","app_build":"1","measure_sdk_version":"0.0.1","device_low_power_mode":false,"app_unique_id":"sh.measure.DemoApp"},"user_triggered":false},{"id":"bb5ab01e-3460-4721-89ce-d3364174fb96","session_id":"ab9d1005-807f-44db-88a9-2f21591500b8","timestamp":"2025-03-15T04:56:03.380Z","type":"lifecycle_view_controller","lifecycle_view_controller":{"type":"viewWillDisappear","class_name":"CollectionViewController"},"attribute":{"thread_name":"com.apple.main-thread","device_name":"iPhone 16 Pro","device_model":"Simulator iPhone17,1","device_manufacturer":"Apple","device_type":"phone","device_is_foldable":false,"device_is_physical":false,"device_density_dpi":480,"device_width_px":1206,"device_height_px":2622,"device_density":3,"device_locale":"en_IN","os_name":"iOS","os_version":"18.3.1","platform":"ios","network_type":"wifi","network_generation":"unknown","network_provider":"unknown","installation_id":"98aa4d46-a856-45a9-b521-f4566532b572","user_id":"test_user_ios","device_cpu_arch":"arm64e","app_version":"1.0","app_build":"1","measure_sdk_version":"0.0.1","device_low_power_mode":false,"app_unique_id":"sh.measure.DemoApp"},"user_triggered":false},{"id":"af987367-cdd4-4de8-9d68-2c236bdf959f","session_id":"ab9d1005-807f-44db-88a9-2f21591500b8","timestamp":"2025-03-15T04:56:03.382Z","type":"lifecycle_view_controller","lifecycle_view_controller":{"type":"viewWillAppear","class_name":"ObjcDetailViewController"},"attribute":{"thread_name":"com.apple.main-thread","device_name":"iPhone 16 Pro","device_model":"Simulator iPhone17,1","device_manufacturer":"Apple","device_type":"phone","device_is_foldable":false,"device_is_physical":false,"device_density_dpi":480,"device_width_px":1206,"device_height_px":2622,"device_density":3,"device_locale":"en_IN","os_name":"iOS","os_version":"18.3.1","platform":"ios","network_type":"wifi","network_generation":"unknown","network_provider":"unknown","installation_id":"98aa4d46-a856-45a9-b521-f4566532b572","user_id":"test_user_ios","device_cpu_arch":"arm64e","app_version":"1.0","app_build":"1","measure_sdk_version":"0.0.1","device_low_power_mode":false,"app_unique_id":"sh.measure.DemoApp"},"user_triggered":false},{"id":"cdd90f48-b5c5-4c34-be9f-88c8255089a8","session_id":"ab9d1005-807f-44db-88a9-2f21591500b8","timestamp":"2025-03-15T04:56:03.908Z","type":"lifecycle_view_controller","lifecycle_view_controller":{"type":"viewDidDisappear","class_name":"CollectionViewController"},"attribute":{"thread_name":"com.apple.main-thread","device_name":"iPhone 16 Pro","device_model":"Simulator iPhone17,1","device_manufacturer":"Apple","device_type":"phone","device_is_foldable":false,"device_is_physical":false,"device_density_dpi":480,"device_width_px":1206,"device_height_px":2622,"device_density":3,"device_locale":"en_IN","os_name":"iOS","os_version":"18.3.1","platform":"ios","network_type":"wifi","network_generation":"unknown","network_provider":"unknown","installation_id":"98aa4d46-a856-45a9-b521-f4566532b572","user_id":"test_user_ios","device_cpu_arch":"arm64e","app_version":"1.0","app_build":"1","measure_sdk_version":"0.0.1","device_low_power_mode":false,"app_unique_id":"sh.measure.DemoApp"},"user_triggered":false},{"id":"2dbc094e-e98b-4c51-a7a1-02a7897fcda5","session_id":"ab9d1005-807f-44db-88a9-2f21591500b8","timestamp":"2025-03-15T04:56:03.917Z","type":"lifecycle_view_controller","lifecycle_view_controller":{"type":"viewDidAppear","class_name":"ObjcDetailViewController"},"attribute":{"thread_name":"com.apple.main-thread","device_name":"iPhone 16 Pro","device_model":"Simulator iPhone17,1","device_manufacturer":"Apple","device_type":"phone","device_is_foldable":false,"device_is_physical":false,"device_density_dpi":480,"device_width_px":1206,"device_height_px":2622,"device_density":3,"device_locale":"en_IN","os_name":"iOS","os_version":"18.3.1","platform":"ios","network_type":"wifi","network_generation":"unknown","network_provider":"unknown","installation_id":"98aa4d46-a856-45a9-b521-f4566532b572","user_id":"test_user_ios","device_cpu_arch":"arm64e","app_version":"1.0","app_build":"1","measure_sdk_version":"0.0.1","device_low_power_mode":false,"app_unique_id":"sh.measure.DemoApp"},"user_triggered":false},{"id":"33b75824-ed56-45e2-85fe-5c3f961eb2af","session_id":"ab9d1005-807f-44db-88a9-2f21591500b8","timestamp":"2025-03-15T04:56:05.998Z","type":"lifecycle_view_controller","lifecycle_view_controller":{"type":"viewWillDisappear","class_name":"ObjcDetailViewController"},"attribute":{"thread_name":"com.apple.main-thread","device_name":"iPhone 16 Pro","device_model":"Simulator iPhone17,1","device_manufacturer":"Apple","device_type":"phone","device_is_foldable":false,"device_is_physical":false,"device_density_dpi":480,"device_width_px":1206,"device_height_px":2622,"device_density":3,"device_locale":"en_IN","os_name":"iOS","os_version":"18.3.1","platform":"ios","network_type":"wifi","network_generation":"unknown","network_provider":"unknown","installation_id":"98aa4d46-a856-45a9-b521-f4566532b572","user_id":"test_user_ios","device_cpu_arch":"arm64e","app_version":"1.0","app_build":"1","measure_sdk_version":"0.0.1","device_low_power_mode":false,"app_unique_id":"sh.measure.DemoApp"},"user_triggered":false},{"id":"5ee95590-d98d-49ea-a3d7-72aabe522e57","session_id":"ab9d1005-807f-44db-88a9-2f21591500b8","timestamp":"2025-03-15T04:56:06.002Z","type":"lifecycle_view_controller","lifecycle_view_controller":{"type":"viewWillAppear","class_name":"ViewController"},"attribute":{"thread_name":"com.apple.main-thread","device_name":"iPhone 16 Pro","device_model":"Simulator iPhone17,1","device_manufacturer":"Apple","device_type":"phone","device_is_foldable":false,"device_is_physical":false,"device_density_dpi":480,"device_width_px":1206,"device_height_px":2622,"device_density":3,"device_locale":"en_IN","os_name":"iOS","os_version":"18.3.1","platform":"ios","network_type":"wifi","network_generation":"unknown","network_provider":"unknown","installation_id":"98aa4d46-a856-45a9-b521-f4566532b572","user_id":"test_user_ios","device_cpu_arch":"arm64e","app_version":"1.0","app_build":"1","measure_sdk_version":"0.0.1","device_low_power_mode":false,"app_unique_id":"sh.measure.DemoApp"},"user_triggered":false},{"id":"2e43c041-cd31-4c21-8216-e023485b694a","session_id":"ab9d1005-807f-44db-88a9-2f21591500b8","timestamp":"2025-03-15T04:56:06.520Z","type":"lifecycle_view_controller","lifecycle_view_controller":{"type":"viewDidDisappear","class_name":"ObjcDetailViewController"},"attribute":{"thread_name":"com.apple.main-thread","device_name":"iPhone 16 Pro","device_model":"Simulator iPhone17,1","device_manufacturer":"Apple","device_type":"phone","device_is_foldable":false,"device_is_physical":false,"device_density_dpi":480,"device_width_px":1206,"device_height_px":2622,"device_density":3,"device_locale":"en_IN","os_name":"iOS","os_version":"18.3.1","platform":"ios","network_type":"wifi","network_generation":"unknown","network_provider":"unknown","installation_id":"98aa4d46-a856-45a9-b521-f4566532b572","user_id":"test_user_ios","device_cpu_arch":"arm64e","app_version":"1.0","app_build":"1","measure_sdk_version":"0.0.1","device_low_power_mode":false,"app_unique_id":"sh.measure.DemoApp"},"user_triggered":false},{"id":"d5df62de-5066-4714-a743-34b5ec1f958a","session_id":"ab9d1005-807f-44db-88a9-2f21591500b8","timestamp":"2025-03-15T04:56:06.529Z","type":"lifecycle_view_controller","lifecycle_view_controller":{"type":"viewDidAppear","class_name":"ViewController"},"attribute":{"thread_name":"com.apple.main-thread","device_name":"iPhone 16 Pro","device_model":"Simulator iPhone17,1","device_manufacturer":"Apple","device_type":"phone","device_is_foldable":false,"device_is_physical":false,"device_density_dpi":480,"device_width_px":1206,"device_height_px":2622,"device_density":3,"device_locale":"en_IN","os_name":"iOS","os_version":"18.3.1","platform":"ios","network_type":"wifi","network_generation":"unknown","network_provider":"unknown","installation_id":"98aa4d46-a856-45a9-b521-f4566532b572","user_id":"test_user_ios","device_cpu_arch":"arm64e","app_version":"1.0","app_build":"1","measure_sdk_version":"0.0.1","device_low_power_mode":false,"app_unique_id":"sh.measure.DemoApp"},"user_triggered":false},{"id":"6f2bdb4e-4a98-4186-bc37-0f398a492215","session_id":"ab9d1005-807f-44db-88a9-2f21591500b8","timestamp":"2025-03-15T04:56:06.533Z","type":"screen_view","screen_view":{"name":"Home"},"attribute":{"thread_name":"com.apple.main-thread","device_name":"iPhone 16 Pro","device_model":"Simulator iPhone17,1","device_manufacturer":"Apple","device_type":"phone","device_is_foldable":false,"device_is_physical":false,"device_density_dpi":480,"device_width_px":1206,"device_height_px":2622,"device_density":3,"device_locale":"en_IN","os_name":"iOS","os_version":"18.3.1","platform":"ios","network_type":"wifi","network_generation":"unknown","network_provider":"unknown","installation_id":"98aa4d46-a856-45a9-b521-f4566532b572","user_id":"test_user_ios","device_cpu_arch":"arm64e","app_version":"1.0","app_build":"1","measure_sdk_version":"0.0.1","device_low_power_mode":false,"app_unique_id":"sh.measure.DemoApp"},"user_triggered":true},{"id":"3efc3a59-0b46-4a01-9508-cb02ba2d88c8","session_id":"ab9d1005-807f-44db-88a9-2f21591500b8","timestamp":"2025-03-15T04:56:07.662Z","type":"lifecycle_view_controller","lifecycle_view_controller":{"type":"viewDidLoad","class_name":"ControlsViewController"},"attribute":{"thread_name":"com.apple.main-thread","device_name":"iPhone 16 Pro","device_model":"Simulator iPhone17,1","device_manufacturer":"Apple","device_type":"phone","device_is_foldable":false,"device_is_physical":false,"device_density_dpi":480,"device_width_px":1206,"device_height_px":2622,"device_density":3,"device_locale":"en_IN","os_name":"iOS","os_version":"18.3.1","platform":"ios","network_type":"wifi","network_generation":"unknown","network_provider":"unknown","installation_id":"98aa4d46-a856-45a9-b521-f4566532b572","user_id":"test_user_ios","device_cpu_arch":"arm64e","app_version":"1.0","app_build":"1","measure_sdk_version":"0.0.1","device_low_power_mode":false,"app_unique_id":"sh.measure.DemoApp"},"user_triggered":false},{"id":"f0802f01-15cf-46a4-ba49-31129bbe27c0","session_id":"ab9d1005-807f-44db-88a9-2f21591500b8","timestamp":"2025-03-15T04:56:07.666Z","type":"lifecycle_view_controller","lifecycle_view_controller":{"type":"viewWillDisappear","class_name":"ViewController"},"attribute":{"thread_name":"com.apple.main-thread","device_name":"iPhone 16 Pro","device_model":"Simulator iPhone17,1","device_manufacturer":"Apple","device_type":"phone","device_is_foldable":false,"device_is_physical":false,"device_density_dpi":480,"device_width_px":1206,"device_height_px":2622,"device_density":3,"device_locale":"en_IN","os_name":"iOS","os_version":"18.3.1","platform":"ios","network_type":"wifi","network_generation":"unknown","network_provider":"unknown","installation_id":"98aa4d46-a856-45a9-b521-f4566532b572","user_id":"test_user_ios","device_cpu_arch":"arm64e","app_version":"1.0","app_build":"1","measure_sdk_version":"0.0.1","device_low_power_mode":false,"app_unique_id":"sh.measure.DemoApp"},"user_triggered":false},{"id":"811c54ba-c5a0-45fa-8ba3-2a9d98af1f6b","session_id":"ab9d1005-807f-44db-88a9-2f21591500b8","timestamp":"2025-03-15T04:56:07.670Z","type":"lifecycle_view_controller","lifecycle_view_controller":{"type":"viewWillAppear","class_name":"ControlsViewController"},"attribute":{"thread_name":"com.apple.main-thread","device_name":"iPhone 16 Pro","device_model":"Simulator iPhone17,1","device_manufacturer":"Apple","device_type":"phone","device_is_foldable":false,"device_is_physical":false,"device_density_dpi":480,"device_width_px":1206,"device_height_px":2622,"device_density":3,"device_locale":"en_IN","os_name":"iOS","os_version":"18.3.1","platform":"ios","network_type":"wifi","network_generation":"unknown","network_provider":"unknown","installation_id":"98aa4d46-a856-45a9-b521-f4566532b572","user_id":"test_user_ios","device_cpu_arch":"arm64e","app_version":"1.0","app_build":"1","measure_sdk_version":"0.0.1","device_low_power_mode":false,"app_unique_id":"sh.measure.DemoApp"},"user_triggered":false},{"id":"6bd7696f-14a7-4e47-98a4-3ef2b7f36fc3","session_id":"ab9d1005-807f-44db-88a9-2f21591500b8","timestamp":"2025-03-15T04:56:08.191Z","type":"lifecycle_view_controller","lifecycle_view_controller":{"type":"viewDidDisappear","class_name":"ViewController"},"attribute":{"thread_name":"com.apple.main-thread","device_name":"iPhone 16 Pro","device_model":"Simulator iPhone17,1","device_manufacturer":"Apple","device_type":"phone","device_is_foldable":false,"device_is_physical":false,"device_density_dpi":480,"device_width_px":1206,"device_height_px":2622,"device_density":3,"device_locale":"en_IN","os_name":"iOS","os_version":"18.3.1","platform":"ios","network_type":"wifi","network_generation":"unknown","network_provider":"unknown","installation_id":"98aa4d46-a856-45a9-b521-f4566532b572","user_id":"test_user_ios","device_cpu_arch":"arm64e","app_version":"1.0","app_build":"1","measure_sdk_version":"0.0.1","device_low_power_mode":false,"app_unique_id":"sh.measure.DemoApp"},"user_triggered":false},{"id":"f39eb24a-d140-40eb-9375-e953d5a43bc2","session_id":"ab9d1005-807f-44db-88a9-2f21591500b8","timestamp":"2025-03-15T04:56:08.203Z","type":"lifecycle_view_controller","lifecycle_view_controller":{"type":"viewDidAppear","class_name":"ControlsViewController"},"attribute":{"thread_name":"com.apple.main-thread","device_name":"iPhone 16 Pro","device_model":"Simulator iPhone17,1","device_manufacturer":"Apple","device_type":"phone","device_is_foldable":false,"device_is_physical":false,"device_density_dpi":480,"device_width_px":1206,"device_height_px":2622,"device_density":3,"device_locale":"en_IN","os_name":"iOS","os_version":"18.3.1","platform":"ios","network_type":"wifi","network_generation":"unknown","network_provider":"unknown","installation_id":"98aa4d46-a856-45a9-b521-f4566532b572","user_id":"test_user_ios","device_cpu_arch":"arm64e","app_version":"1.0","app_build":"1","measure_sdk_version":"0.0.1","device_low_power_mode":false,"app_unique_id":"sh.measure.DemoApp"},"user_triggered":false},{"id":"39a249b0-90bd-4b16-af06-3a0fa096ab16","session_id":"ab9d1005-807f-44db-88a9-2f21591500b8","timestamp":"2025-03-15T04:56:09.416Z","type":"lifecycle_view_controller","lifecycle_view_controller":{"type":"viewWillDisappear","class_name":"ControlsViewController"},"attribute":{"thread_name":"com.apple.main-thread","device_name":"iPhone 16 Pro","device_model":"Simulator iPhone17,1","device_manufacturer":"Apple","device_type":"phone","device_is_foldable":false,"device_is_physical":false,"device_density_dpi":480,"device_width_px":1206,"device_height_px":2622,"device_density":3,"device_locale":"en_IN","os_name":"iOS","os_version":"18.3.1","platform":"ios","network_type":"wifi","network_generation":"unknown","network_provider":"unknown","installation_id":"98aa4d46-a856-45a9-b521-f4566532b572","user_id":"test_user_ios","device_cpu_arch":"arm64e","app_version":"1.0","app_build":"1","measure_sdk_version":"0.0.1","device_low_power_mode":false,"app_unique_id":"sh.measure.DemoApp"},"user_triggered":false},{"id":"3edf16da-124f-4465-abf9-084d100be976","session_id":"ab9d1005-807f-44db-88a9-2f21591500b8","timestamp":"2025-03-15T04:56:09.420Z","type":"lifecycle_view_controller","lifecycle_view_controller":{"type":"viewWillAppear","class_name":"ViewController"},"attribute":{"thread_name":"com.apple.main-thread","device_name":"iPhone 16 Pro","device_model":"Simulator iPhone17,1","device_manufacturer":"Apple","device_type":"phone","device_is_foldable":false,"device_is_physical":false,"device_density_dpi":480,"device_width_px":1206,"device_height_px":2622,"device_density":3,"device_locale":"en_IN","os_name":"iOS","os_version":"18.3.1","platform":"ios","network_type":"wifi","network_generation":"unknown","network_provider":"unknown","installation_id":"98aa4d46-a856-45a9-b521-f4566532b572","user_id":"test_user_ios","device_cpu_arch":"arm64e","app_version":"1.0","app_build":"1","measure_sdk_version":"0.0.1","device_low_power_mode":false,"app_unique_id":"sh.measure.DemoApp"},"user_triggered":false},{"id":"d8807129-8201-4426-bb81-00772564591d","session_id":"ab9d1005-807f-44db-88a9-2f21591500b8","timestamp":"2025-03-15T04:56:09.935Z","type":"lifecycle_view_controller","lifecycle_view_controller":{"type":"viewDidDisappear","class_name":"ControlsViewController"},"attribute":{"thread_name":"com.apple.main-thread","device_name":"iPhone 16 Pro","device_model":"Simulator iPhone17,1","device_manufacturer":"Apple","device_type":"phone","device_is_foldable":false,"device_is_physical":false,"device_density_dpi":480,"device_width_px":1206,"device_height_px":2622,"device_density":3,"device_locale":"en_IN","os_name":"iOS","os_version":"18.3.1","platform":"ios","network_type":"wifi","network_generation":"unknown","network_provider":"unknown","installation_id":"98aa4d46-a856-45a9-b521-f4566532b572","user_id":"test_user_ios","device_cpu_arch":"arm64e","app_version":"1.0","app_build":"1","measure_sdk_version":"0.0.1","device_low_power_mode":false,"app_unique_id":"sh.measure.DemoApp"},"user_triggered":false},{"id":"63b7fb85-ba85-4284-bd44-176ac0b1f67c","session_id":"ab9d1005-807f-44db-88a9-2f21591500b8","timestamp":"2025-03-15T04:56:09.945Z","type":"lifecycle_view_controller","lifecycle_view_controller":{"type":"viewDidAppear","class_name":"ViewController"},"attribute":{"thread_name":"com.apple.main-thread","device_name":"iPhone 16 Pro","device_model":"Simulator iPhone17,1","device_manufacturer":"Apple","device_type":"phone","device_is_foldable":false,"device_is_physical":false,"device_density_dpi":480,"device_width_px":1206,"device_height_px":2622,"device_density":3,"device_locale":"en_IN","os_name":"iOS","os_version":"18.3.1","platform":"ios","network_type":"wifi","network_generation":"unknown","network_provider":"unknown","installation_id":"98aa4d46-a856-45a9-b521-f4566532b572","user_id":"test_user_ios","device_cpu_arch":"arm64e","app_version":"1.0","app_build":"1","measure_sdk_version":"0.0.1","device_low_power_mode":false,"app_unique_id":"sh.measure.DemoApp"},"user_triggered":false},{"id":"4341a256-9945-4fbd-9951-4c6ce329c079","session_id":"ab9d1005-807f-44db-88a9-2f21591500b8","timestamp":"2025-03-15T04:56:09.949Z","type":"screen_view","screen_view":{"name":"Home"},"attribute":{"thread_name":"com.apple.main-thread","device_name":"iPhone 16 Pro","device_model":"Simulator iPhone17,1","device_manufacturer":"Apple","device_type":"phone","device_is_foldable":false,"device_is_physical":false,"device_density_dpi":480,"device_width_px":1206,"device_height_px":2622,"device_density":3,"device_locale":"en_IN","os_name":"iOS","os_version":"18.3.1","platform":"ios","network_type":"wifi","network_generation":"unknown","network_provider":"unknown","installation_id":"98aa4d46-a856-45a9-b521-f4566532b572","user_id":"test_user_ios","device_cpu_arch":"arm64e","app_version":"1.0","app_build":"1","measure_sdk_version":"0.0.1","device_low_power_mode":false,"app_unique_id":"sh.measure.DemoApp"},"user_triggered":true},{"id":"93b810fc-931c-46df-87ed-018dd25fca0f","session_id":"ab9d1005-807f-44db-88a9-2f21591500b8","timestamp":"2025-03-15T04:56:10.810Z","type":"lifecycle_view_controller","lifecycle_view_controller":{"type":"viewDidLoad","class_name":"CollectionViewController"},"attribute":{"thread_name":"com.apple.main-thread","device_name":"iPhone 16 Pro","device_model":"Simulator iPhone17,1","device_manufacturer":"Apple","device_type":"phone","device_is_foldable":false,"device_is_physical":false,"device_density_dpi":480,"device_width_px":1206,"device_height_px":2622,"device_density":3,"device_locale":"en_IN","os_name":"iOS","os_version":"18.3.1","platform":"ios","network_type":"wifi","network_generation":"unknown","network_provider":"unknown","installation_id":"98aa4d46-a856-45a9-b521-f4566532b572","user_id":"test_user_ios","device_cpu_arch":"arm64e","app_version":"1.0","app_build":"1","measure_sdk_version":"0.0.1","device_low_power_mode":false,"app_unique_id":"sh.measure.DemoApp"},"user_triggered":false},{"id":"60163c96-3bde-44c8-8aa5-8afc492e3b60","session_id":"ab9d1005-807f-44db-88a9-2f21591500b8","timestamp":"2025-03-15T04:56:10.815Z","type":"lifecycle_view_controller","lifecycle_view_controller":{"type":"viewWillDisappear","class_name":"ViewController"},"attribute":{"thread_name":"com.apple.main-thread","device_name":"iPhone 16 Pro","device_model":"Simulator iPhone17,1","device_manufacturer":"Apple","device_type":"phone","device_is_foldable":false,"device_is_physical":false,"device_density_dpi":480,"device_width_px":1206,"device_height_px":2622,"device_density":3,"device_locale":"en_IN","os_name":"iOS","os_version":"18.3.1","platform":"ios","network_type":"wifi","network_generation":"unknown","network_provider":"unknown","installation_id":"98aa4d46-a856-45a9-b521-f4566532b572","user_id":"test_user_ios","device_cpu_arch":"arm64e","app_version":"1.0","app_build":"1","measure_sdk_version":"0.0.1","device_low_power_mode":false,"app_unique_id":"sh.measure.DemoApp"},"user_triggered":false},{"id":"0946e3ac-e1f6-464f-97f1-f9332b8645df","session_id":"ab9d1005-807f-44db-88a9-2f21591500b8","timestamp":"2025-03-15T04:56:10.818Z","type":"lifecycle_view_controller","lifecycle_view_controller":{"type":"viewWillAppear","class_name":"CollectionViewController"},"attribute":{"thread_name":"com.apple.main-thread","device_name":"iPhone 16 Pro","device_model":"Simulator iPhone17,1","device_manufacturer":"Apple","device_type":"phone","device_is_foldable":false,"device_is_physical":false,"device_density_dpi":480,"device_width_px":1206,"device_height_px":2622,"device_density":3,"device_locale":"en_IN","os_name":"iOS","os_version":"18.3.1","platform":"ios","network_type":"wifi","network_generation":"unknown","network_provider":"unknown","installation_id":"98aa4d46-a856-45a9-b521-f4566532b572","user_id":"test_user_ios","device_cpu_arch":"arm64e","app_version":"1.0","app_build":"1","measure_sdk_version":"0.0.1","device_low_power_mode":false,"app_unique_id":"sh.measure.DemoApp"},"user_triggered":false},{"id":"8068467d-78e2-4ccd-a659-ccfbe7671114","session_id":"ab9d1005-807f-44db-88a9-2f21591500b8","timestamp":"2025-03-15T04:56:11.344Z","type":"lifecycle_view_controller","lifecycle_view_controller":{"type":"viewDidDisappear","class_name":"ViewController"},"attribute":{"thread_name":"com.apple.main-thread","device_name":"iPhone 16 Pro","device_model":"Simulator iPhone17,1","device_manufacturer":"Apple","device_type":"phone","device_is_foldable":false,"device_is_physical":false,"device_density_dpi":480,"device_width_px":1206,"device_height_px":2622,"device_density":3,"device_locale":"en_IN","os_name":"iOS","os_version":"18.3.1","platform":"ios","network_type":"wifi","network_generation":"unknown","network_provider":"unknown","installation_id":"98aa4d46-a856-45a9-b521-f4566532b572","user_id":"test_user_ios","device_cpu_arch":"arm64e","app_version":"1.0","app_build":"1","measure_sdk_version":"0.0.1","device_low_power_mode":false,"app_unique_id":"sh.measure.DemoApp"},"user_triggered":false},{"id":"19194014-04d4-4c69-8113-8bc6e3b54a19","session_id":"ab9d1005-807f-44db-88a9-2f21591500b8","timestamp":"2025-03-15T04:56:11.358Z","type":"lifecycle_view_controller","lifecycle_view_controller":{"type":"viewDidAppear","class_name":"CollectionViewController"},"attribute":{"thread_name":"com.apple.main-thread","device_name":"iPhone 16 Pro","device_model":"Simulator iPhone17,1","device_manufacturer":"Apple","device_type":"phone","device_is_foldable":false,"device_is_physical":false,"device_density_dpi":480,"device_width_px":1206,"device_height_px":2622,"device_density":3,"device_locale":"en_IN","os_name":"iOS","os_version":"18.3.1","platform":"ios","network_type":"wifi","network_generation":"unknown","network_provider":"unknown","installation_id":"98aa4d46-a856-45a9-b521-f4566532b572","user_id":"test_user_ios","device_cpu_arch":"arm64e","app_version":"1.0","app_build":"1","measure_sdk_version":"0.0.1","device_low_power_mode":false,"app_unique_id":"sh.measure.DemoApp"},"user_triggered":false}]}